arduino_colab_bridge/arduino_colab_server.py
arduino_colab_bridge-0.1.0.dist-info/licenses/LICENSE
arduino_colab_bridge-0.1.0.dist-info/METADATA
arduino_colab_bridge-0.1.0.dist-info/WHEEL
arduino_colab_bridge-0.1.0.dist-info/top_level.txt
arduino_colab_bridge-0.1.0.dist-info/RECORD
