Metadata-Version: 2.4
Name: arduino-colab-bridge
Version: 0.1.0
Summary: HW bridge for Arduino Colab
Author-email: Jiri Konecny <jiri.konecny@vsb.cz>
License-Expression: MIT
Project-URL: Homepage, https://github.com/sgtkingo/ArduinoColab
Project-URL: Repository, https://github.com/sgtkingo/ArduinoColab
Project-URL: Issues, https://github.com/sgtkingo/ArduinoColab/issues
Keywords: arduino,esp32,jupyter,magics,notebook
Classifier: Development Status :: 3 - Alpha
Classifier: Intended Audience :: Developers
Classifier: Topic :: Software Development :: Embedded Systems
Classifier: Topic :: Education
Classifier: Programming Language :: Python :: 3
Classifier: Programming Language :: Python :: 3.10
Requires-Python: >=3.10
License-File: LICENSE
Requires-Dist: pyserial>=3.5
Requires-Dist: flask>=3.1.2
Requires-Dist: arduino-colab-kernel>=0.1.52
Dynamic: license-file
